timeless_loop/__init__.py
timeless_loop-0.2.0.dist-info/WHEEL
timeless_loop-0.2.0.dist-info/METADATA
timeless_loop-0.2.0.dist-info/RECORD
