Metadata-Version: 2.1
Name: timeless-loop
Version: 0.2.0
Summary: 
Author: Pedro Batista
Author-email: pedrovhb@gmail.com
Requires-Python: >=3.9,<4.0
Classifier: Programming Language :: Python :: 3
Classifier: Programming Language :: Python :: 3.9
Classifier: Programming Language :: Python :: 3.10
Classifier: Programming Language :: Python :: 3.11
